mycalc/calculator.py
mycalc/setup.py
oss_test-0.0.3.dist-info/METADATA
oss_test-0.0.3.dist-info/WHEEL
oss_test-0.0.3.dist-info/top_level.txt
oss_test-0.0.3.dist-info/RECORD
