Metadata-Version: 2.1
Name: oss-test
Version: 0.0.3
Summary: oss-dev my calculator 0001
Home-page: https://github.com/Kim-DO-Hyeong/calc0001
Download-URL: https://github.com/Kim-DO-Hyeong/calc0001/archive/refs/tags/v0.0.1.zip
Author: dohyeong
License: UNKNOWN
Platform: UNKNOWN
Classifier: Programming Language :: Python :: 3
